puttykeys/__init__.py
puttykeys/__main__.py
puttykeys-1.0.3.dist-info/DESCRIPTION.rst
puttykeys-1.0.3.dist-info/METADATA
puttykeys-1.0.3.dist-info/RECORD
puttykeys-1.0.3.dist-info/WHEEL
puttykeys-1.0.3.dist-info/metadata.json
puttykeys-1.0.3.dist-info/top_level.txt
